MANIFEST.in
README.rst
setup.py
test_requirements.txt
orcoursetrion/__init__.py
orcoursetrion/cmd.py
orcoursetrion/config.py
orcoursetrion.egg-info/PKG-INFO
orcoursetrion.egg-info/SOURCES.txt
orcoursetrion.egg-info/dependency_links.txt
orcoursetrion.egg-info/entry_points.txt
orcoursetrion.egg-info/requires.txt
orcoursetrion.egg-info/top_level.txt
orcoursetrion.egg-info/zip-safe
orcoursetrion/actions/__init__.py
orcoursetrion/actions/github.py
orcoursetrion/lib/__init__.py
orcoursetrion/lib/github.py
orcoursetrion/tests/__init__.py
orcoursetrion/tests/base.py
orcoursetrion/tests/test_action.py
orcoursetrion/tests/test_cmd.py
orcoursetrion/tests/test_core.py
orcoursetrion/tests/test_github.py