Metadata-Version: 1.1
Name: orcoursetrion
Version: 0.2.1
Summary: Automatic course provisioning for the edx-platform using github and zendesk.
Home-page: http://orcoursetrion.rtfd.org
Author: MIT Office of Digital Learning
Author-email: odl-engineering@mit.edu
License: BSD Simplified
Platform: UNKNOWN
Classifier: Development Status :: 2 - Pre-Alpha
Classifier: Intended Audience :: Information Technology
Classifier: License :: OSI Approved :: BSD License
Classifier: Operating System :: POSIX :: Linux
